simplegraph/__init__.py
simplegraph/graph.py
simplegraph/inference.py
simplegraph/rules.py
simplegraph/spin.py
simplegraph/tests/__init__.py
simplegraph/tests/data.py
simplegraph/tests/test_graph.py
simplegraph-1.0.1.dist-info/DESCRIPTION.rst
simplegraph-1.0.1.dist-info/METADATA
simplegraph-1.0.1.dist-info/RECORD
simplegraph-1.0.1.dist-info/WHEEL
simplegraph-1.0.1.dist-info/metadata.json
simplegraph-1.0.1.dist-info/top_level.txt
