Metadata-Version: 2.0
Name: simplegraph
Version: 1.0.1
Summary: Simple RDF processing in Python
Home-page: https://github.com/pypa/sampleproject
Author: John Taylor
Author-email: johtaylo@microsoft.com
License: UNKNOWN
Keywords: graph rdf inference rdfs owl ontology
Platform: UNKNOWN
Classifier: Development Status :: 3 - Alpha
Classifier: Intended Audience :: Developers
Classifier: Topic :: Software Development :: Build Tools
Classifier: License :: OSI Approved :: MIT License
Classifier: Programming Language :: Python :: 3.6
